yoix/__init__.py
yoix/cli.py
yoix/core.py
yoix/asset/__init__.py
yoix/asset/manager.py
yoix/config/__init__.py
yoix/config/defaults.py
yoix/config/manager.py
yoix/pm/__init__.py
yoix/pm/pm.py
yoix/pm/security.py
yoix/pm/api/__init__.py
yoix/pm/api/api.py
yoix/post/__init__.py
yoix/post/processor.py
yoix/template/__init__.py
yoix/template/manager.py
yoix-0.2.0.dist-info/licenses/LICENSE
yoix-0.2.0.dist-info/METADATA
yoix-0.2.0.dist-info/WHEEL
yoix-0.2.0.dist-info/entry_points.txt
yoix-0.2.0.dist-info/top_level.txt
yoix-0.2.0.dist-info/RECORD
