Metadata-Version: 2.4
Name: yoix
Version: 0.2.0
Summary: Pythonic static site generator designed for minimalists
Home-page: https://github.com/crock/yoix.py
Author: Alex Crocker
Classifier: Programming Language :: Python :: 3
Classifier: License :: OSI Approved :: MIT License
Classifier: Operating System :: OS Independent
Requires-Python: >=3.8
License-File: LICENSE
Requires-Dist: click>=8.0.0
Requires-Dist: mistune
Requires-Dist: python-frontmatter
Requires-Dist: python-slugify
Requires-Dist: tomli>=1.1.0
Requires-Dist: yoix-pi==1.0.0
Requires-Dist: pybars3==0.9.7
Provides-Extra: dev
Requires-Dist: pytest>=7.0.0; extra == "dev"
Requires-Dist: pytest-cov>=4.0.0; extra == "dev"
Dynamic: author
Dynamic: classifier
Dynamic: description
Dynamic: description-content-type
Dynamic: home-page
Dynamic: license-file
Dynamic: provides-extra
Dynamic: requires-dist
Dynamic: requires-python
Dynamic: summary
